Metadata-Version: 2.1
Name: mtdd
Version: 0.0.2
Summary: TDD framework
Author: Milan Neubert, Felipe Bombardelli
Author-email: felipebombardelli@gmail.com
Classifier: Programming Language :: Python :: 3
Classifier: Programming Language :: Python :: 3.7
Classifier: Programming Language :: Python :: 3.8
Classifier: Topic :: Software Development :: Libraries :: Python Modules
Classifier: License :: OSI Approved :: MIT License
Classifier: Operating System :: OS Independent
Requires-Python: >=3
License-File: LICENSE
